gam_purification/__init__.py
gam_purification/purify.py
gam_purification/test_purify.py
gam_purification/test_utils.py
gam_purification/utils.py
gam_purification/models/__init__.py
gam_purification/models/ebm.py
gam_purification/models/tests.py
gam_purification/models/xgb.py
gam_purification-0.0.1.dist-info/LICENSE
gam_purification-0.0.1.dist-info/METADATA
gam_purification-0.0.1.dist-info/WHEEL
gam_purification-0.0.1.dist-info/top_level.txt
gam_purification-0.0.1.dist-info/RECORD
