Metadata-Version: 2.1
Name: gam-purification
Version: 0.0.1
Summary: Purify additive models.
Home-page: https://github.com/blengerich/gam_purification
Author: Ben Lengerich
License-File: LICENSE
Requires-Dist: numpy
Requires-Dist: scikit-learn
Requires-Dist: matplotlib
Requires-Dist: pandas
Requires-Dist: numpy (>=1.19.2)
Requires-Dist: ipywidgets
Requires-Dist: interpret
